setup.cfg
setup.py
keyword_only_args/__init__.py
keyword_only_args/keyword_only_args.py
keyword_only_args/tests.py
keyword_only_args.egg-info/PKG-INFO
keyword_only_args.egg-info/SOURCES.txt
keyword_only_args.egg-info/dependency_links.txt
keyword_only_args.egg-info/requires.txt
keyword_only_args.egg-info/top_level.txt