Metadata-Version: 1.1
Name: keyword-only-args
Version: 1.0
Summary: A decorator to use keyword-only arguments in Python 2 and 3.
Home-page: https://github.com/ceridwen/keyword_only_args
Author: Ceridwen
Author-email: ceridwenv@gmail.com
License: MIT
Download-URL: https://github.com/ceridwen/keyword_only_args/tarball/1.0
Keywords: arguments,decorator,keyword,keyword_only
Platform: UNKNOWN
Classifier: Development Status :: 5 - Production/Stable
Classifier: License :: OSI Approved :: MIT License
Classifier: Programming Language :: Python
Classifier: Programming Language :: Python :: 2
Classifier: Programming Language :: Python :: 3
Classifier: Topic :: Software Development
